PythonHeimaoBiancheng1142XuanhunGongzuoshi/README.md
PythonHeimaoBiancheng1142XuanhunGongzuoshi/__init__.py
PythonHeimaoBiancheng1142XuanhunGongzuoshi/__main__.py
PythonHeimaoBiancheng1142XuanhunGongzuoshi/file.epub
PythonHeimaoBiancheng1142XuanhunGongzuoshi/index.html
PythonHeimaoBiancheng1142XuanhunGongzuoshi/css/__init__.py
PythonHeimaoBiancheng1142XuanhunGongzuoshi/css/annotations.css
PythonHeimaoBiancheng1142XuanhunGongzuoshi/css/main.css
PythonHeimaoBiancheng1142XuanhunGongzuoshi/css/normalize.css
PythonHeimaoBiancheng1142XuanhunGongzuoshi/css/popup.css
PythonHeimaoBiancheng1142XuanhunGongzuoshi/font/__init__.py
PythonHeimaoBiancheng1142XuanhunGongzuoshi/font/fontello.eot
PythonHeimaoBiancheng1142XuanhunGongzuoshi/font/fontello.svg
PythonHeimaoBiancheng1142XuanhunGongzuoshi/font/fontello.ttf
PythonHeimaoBiancheng1142XuanhunGongzuoshi/font/fontello.woff
PythonHeimaoBiancheng1142XuanhunGongzuoshi/img/__init__.py
PythonHeimaoBiancheng1142XuanhunGongzuoshi/img/annotator-glyph-sprite.png
PythonHeimaoBiancheng1142XuanhunGongzuoshi/img/annotator-icon-sprite.png
PythonHeimaoBiancheng1142XuanhunGongzuoshi/img/apple-touch-icon.png
PythonHeimaoBiancheng1142XuanhunGongzuoshi/img/cancelfullscreen.png
PythonHeimaoBiancheng1142XuanhunGongzuoshi/img/close.png
PythonHeimaoBiancheng1142XuanhunGongzuoshi/img/fullscreen.png
PythonHeimaoBiancheng1142XuanhunGongzuoshi/img/loader.gif
PythonHeimaoBiancheng1142XuanhunGongzuoshi/img/menu-icon.png
PythonHeimaoBiancheng1142XuanhunGongzuoshi/img/save.png
PythonHeimaoBiancheng1142XuanhunGongzuoshi/img/saved.png
PythonHeimaoBiancheng1142XuanhunGongzuoshi/img/settings-s.png
PythonHeimaoBiancheng1142XuanhunGongzuoshi/img/settings.png
PythonHeimaoBiancheng1142XuanhunGongzuoshi/img/star.png
PythonHeimaoBiancheng1142XuanhunGongzuoshi/js/__init__.py
PythonHeimaoBiancheng1142XuanhunGongzuoshi/js/epub.js
PythonHeimaoBiancheng1142XuanhunGongzuoshi/js/epub.min.js
PythonHeimaoBiancheng1142XuanhunGongzuoshi/js/epub.min.map
python_heimao_biancheng_1_1_4_2_xuanhun_gongzuoshi-2024.3.2.0.dist-info/METADATA
python_heimao_biancheng_1_1_4_2_xuanhun_gongzuoshi-2024.3.2.0.dist-info/WHEEL
python_heimao_biancheng_1_1_4_2_xuanhun_gongzuoshi-2024.3.2.0.dist-info/entry_points.txt
python_heimao_biancheng_1_1_4_2_xuanhun_gongzuoshi-2024.3.2.0.dist-info/top_level.txt
python_heimao_biancheng_1_1_4_2_xuanhun_gongzuoshi-2024.3.2.0.dist-info/RECORD
